citric/__init__.py
citric/_compat.py
citric/client.py
citric/enums.py
citric/exceptions.py
citric/method.py
citric/objects.py
citric/py.typed
citric/session.py
citric/types.py
citric/_rest/__init__.py
citric/_rest/client.py
citric-1.4.0.dist-info/METADATA
citric-1.4.0.dist-info/WHEEL
citric-1.4.0.dist-info/licenses/AUTHORS.md
citric-1.4.0.dist-info/licenses/LICENSE
citric-1.4.0.dist-info/RECORD
