Metadata-Version: 2.4
Name: citric
Version: 1.4.0
Summary: A client to the LimeSurvey Remote Control API 2, written in modern Python.
Project-URL: Documentation, https://citric.readthedocs.io
Project-URL: Funding, https://github.com/sponsors/edgarrmondragon
Project-URL: Homepage, https://github.com/edgarrmondragon/citric
Project-URL: Issue Tracker, https://github.com/edgarrmondragon/citric/issues
Project-URL: Repository, https://github.com/edgarrmondragon/citric
Author-email: Edgar Ramírez-Mondragón <edgarrm358@gmail.com>
Maintainer-email: Edgar Ramírez-Mondragón <edgarrm358@gmail.com>
License-Expression: MIT
License-File: AUTHORS.md
License-File: LICENSE
Keywords: json-rpc,limesurvey
Classifier: Development Status :: 5 - Production/Stable
Classifier: Intended Audience :: Developers
Classifier: Intended Audience :: Information Technology
Classifier: Intended Audience :: Science/Research
Classifier: Intended Audience :: System Administrators
Classifier: License :: OSI Approved :: MIT License
Classifier: Natural Language :: English
Classifier: Operating System :: OS Independent
Classifier: Programming Language :: Python :: 3 :: Only
Classifier: Programming Language :: Python :: 3.8
Classifier: Programming Language :: Python :: 3.9
Classifier: Programming Language :: Python :: 3.10
Classifier: Programming Language :: Python :: 3.11
Classifier: Programming Language :: Python :: 3.12
Classifier: Programming Language :: Python :: 3.13
Classifier: Programming Language :: Python :: 3.14
Classifier: Programming Language :: Python :: Implementation :: CPython
Classifier: Programming Language :: Python :: Implementation :: PyPy
Classifier: Topic :: Software Development :: Libraries :: Python Modules
Classifier: Typing :: Typed
Requires-Python: >=3.8
Requires-Dist: requests>=2.25.1
